Razlt/__init__.py
Razlt/account.py
Razlt/auth.py
Razlt/client.py
Razlt/device.py
Razlt/friend.py
Razlt/party.py
Razlt/stw_operations.py
razltfn-0.1.4.dist-info/METADATA
razltfn-0.1.4.dist-info/WHEEL
razltfn-0.1.4.dist-info/top_level.txt
razltfn-0.1.4.dist-info/RECORD
