Metadata-Version: 2.4
Name: RazltFn
Version: 0.1.4
Summary: Fortnite API Interact
Author-email: Mxtsouko <mxtsouko@email.com>
License: MIT
Requires-Python: >=3.10
